{
  "title": "Police Manual - Gang Intelligence",
  "chapter": "G",
  "section": "Gang Investigations and Monitoring",
  "category": "Organised Crime",
  "content": "\nPOLICE MANUAL - GANG INTELLIGENCE\n\nGangs in New Zealand:\n- Mongrel Mob\n- Black Power\n- Head Hunters\n- Nomads\n- Hells Angels\n- Other outlaw motorcycle gangs (OMCGs)\n- Ethnic gangs\n- Youth gangs\n\nIntelligence Gathering:\n- Membership lists\n- Hierarchies\n- Territories\n- Criminal activities\n- Associates\n- Alliances and rivalries\n- Recruitment\n- Financial networks\n\nMonitoring:\n- Surveillance\n- Informants\n- Communication analysis\n- Social media monitoring\n- Financial tracking\n- Intelligence sharing\n\nGang Pads (Headquarters):\n- Search warrants\n- Firearms searches\n- Drug searches\n- Association restrictions\n- Firearms Prohibition Orders (FPOs)\n\nFirearms Prohibition Orders (FPOs):\n- Can apply to gang members\n- Prohibits possession of firearms\n- Warrantless search power\n- 10-year duration\n\nPrevention:\n- Exit programs\n- Youth diversion\n- Family support\n- Employment initiatives\n- Community engagement\n\nRelated Legislation:\n- Search and Surveillance Act 2012\n- Firearms Act 1983\n- Arms (Firearms Prohibition Orders) Act 2023\n",
  "key_procedures": [
    "Maintain intelligence database",
    "Monitor gang activities",
    "Execute search warrants on pads",
    "Apply FPOs where appropriate",
    "Coordinate with organized crime units",
    "Support exit programs"
  ],
  "created": "2026-03-03T10:45:46.193389",
  "source": "Police Manual (NZ Police) - Compiled"
}